src/pyopencypher/__init__.py
src/pyopencypher/module.py
pyopencypher-0.1.0.dist-info/LICENSE
pyopencypher-0.1.0.dist-info/METADATA
pyopencypher-0.1.0.dist-info/WHEEL
pyopencypher-0.1.0.dist-info/RECORD
